commons/__init__.py
commons/decorators/__init__.py
commons/decorators/timeout/__init__.py
commons/decorators/timeout/timeout_decorator.py
commons/loggers/__init__.py
commons/loggers/default/__init__.py
commons/loggers/default/logger.py
commons/utils/__init__.py
commons/utils/datetime/__init__.py
commons/utils/datetime/datetime_utils.py
commons/utils/email/__init__.py
commons/utils/email/email_utils.py
commons/utils/encode/__init__.py
commons/utils/encode/automatic_switch_python_version.py
commons/utils/encode/encode_utils.py
commons/utils/image/__init__.py
commons/utils/image/image_utils.py
commons/utils/redis/__init__.py
commons/utils/redis/redis_key_util.py
commons/utils/redis/redis_utils.py
commons/utils/wechat_work/__init__.py
commons/utils/wechat_work/robot_message_builder_util.py
commons/utils/wechat_work/robot_message_sender_util.py
commmons_QrCeric-0.1.0.dist-info/LICENSE
commmons_QrCeric-0.1.0.dist-info/METADATA
commmons_QrCeric-0.1.0.dist-info/WHEEL
commmons_QrCeric-0.1.0.dist-info/entry_points.txt
commmons_QrCeric-0.1.0.dist-info/top_level.txt
commmons_QrCeric-0.1.0.dist-info/RECORD
